optimum/configuration_utils.py
optimum/conftest.py
optimum/modeling_base.py
optimum/quantization_base.py
optimum/runs_base.py
optimum/subpackages.py
optimum/version.py
optimum/bettertransformer/__init__.py
optimum/bettertransformer/transformation.py
optimum/bettertransformer/models/__init__.py
optimum/bettertransformer/models/attention.py
optimum/bettertransformer/models/base.py
optimum/bettertransformer/models/decoder_models.py
optimum/bettertransformer/models/encoder_models.py
optimum/commands/__init__.py
optimum/commands/base.py
optimum/commands/env.py
optimum/commands/optimum_cli.py
optimum/commands/export/__init__.py
optimum/commands/export/base.py
optimum/commands/export/onnx.py
optimum/commands/export/tflite.py
optimum/commands/register/__init__.py
optimum/exporters/__init__.py
optimum/exporters/base.py
optimum/exporters/error_utils.py
optimum/exporters/tasks.py
optimum/exporters/utils.py
optimum/exporters/onnx/__init__.py
optimum/exporters/onnx/__main__.py
optimum/exporters/onnx/_traceable_cache.py
optimum/exporters/onnx/base.py
optimum/exporters/onnx/config.py
optimum/exporters/onnx/constants.py
optimum/exporters/onnx/convert.py
optimum/exporters/onnx/model_configs.py
optimum/exporters/onnx/model_patcher.py
optimum/exporters/onnx/utils.py
optimum/exporters/tflite/__init__.py
optimum/exporters/tflite/__main__.py
optimum/exporters/tflite/base.py
optimum/exporters/tflite/config.py
optimum/exporters/tflite/convert.py
optimum/exporters/tflite/model_configs.py
optimum/fx/__init__.py
optimum/fx/utils.py
optimum/fx/optimization/__init__.py
optimum/fx/optimization/transformations.py
optimum/fx/parallelization/__init__.py
optimum/fx/parallelization/api.py
optimum/fx/parallelization/core.py
optimum/fx/parallelization/decomp.py
optimum/fx/parallelization/passes.py
optimum/fx/parallelization/utils.py
optimum/fx/parallelization/distributed/__init__.py
optimum/fx/parallelization/distributed/dist_ops.py
optimum/fx/parallelization/op_registry/__init__.py
optimum-1.26.1.dist-info/LICENSE
optimum-1.26.1.dist-info/METADATA
optimum-1.26.1.dist-info/WHEEL
optimum-1.26.1.dist-info/entry_points.txt
optimum-1.26.1.dist-info/top_level.txt
optimum-1.26.1.dist-info/RECORD
