Metadata-Version: 2.1
Name: optimum
Version: 1.26.1
Summary: Optimum Library is an extension of the Hugging Face Transformers library, providing a framework to integrate third-party libraries from Hardware Partners and interface with their specific functionality.
Home-page: https://github.com/huggingface/optimum
Author: HuggingFace Inc. Special Ops Team
Author-email: hardware@huggingface.co
License: Apache
Keywords: transformers,quantization,pruning,optimization,training,inference,onnx,onnx runtime,intel,habana,graphcore,neural compressor,ipu,hpu
Classifier: Development Status :: 5 - Production/Stable
Classifier: License :: OSI Approved :: Apache Software License
Classifier: Intended Audience :: Developers
Classifier: Intended Audience :: Education
Classifier: Intended Audience :: Science/Research
Classifier: Operating System :: OS Independent
Classifier: Programming Language :: Python :: 3
Classifier: Programming Language :: Python :: 3.9
Classifier: Programming Language :: Python :: 3.10
Classifier: Programming Language :: Python :: 3.11
Classifier: Topic :: Scientific/Engineering :: Artificial Intelligence
Requires-Python: >=3.9.0
License-File: LICENSE
Requires-Dist: transformers >=4.29
Requires-Dist: torch >=1.11
Requires-Dist: packaging
Requires-Dist: numpy
Requires-Dist: huggingface-hub >=0.8.0
Provides-Extra: amd
Requires-Dist: optimum-amd ; extra == 'amd'
Provides-Extra: benchmark
Requires-Dist: optuna ; extra == 'benchmark'
Requires-Dist: tqdm ; extra == 'benchmark'
Requires-Dist: scikit-learn ; extra == 'benchmark'
Requires-Dist: seqeval ; extra == 'benchmark'
Requires-Dist: torchvision ; extra == 'benchmark'
Requires-Dist: evaluate >=0.2.0 ; extra == 'benchmark'
Provides-Extra: dev
Requires-Dist: accelerate ; extra == 'dev'
Requires-Dist: pytest <=8.0.0 ; extra == 'dev'
Requires-Dist: requests ; extra == 'dev'
Requires-Dist: parameterized ; extra == 'dev'
Requires-Dist: pytest-xdist ; extra == 'dev'
Requires-Dist: Pillow ; extra == 'dev'
Requires-Dist: sacremoses ; extra == 'dev'
Requires-Dist: torchvision ; extra == 'dev'
Requires-Dist: torchaudio ; extra == 'dev'
Requires-Dist: einops ; extra == 'dev'
Requires-Dist: timm ; extra == 'dev'
Requires-Dist: scikit-learn ; extra == 'dev'
Requires-Dist: sentencepiece ; extra == 'dev'
Requires-Dist: rjieba ; extra == 'dev'
Requires-Dist: hf-xet ; extra == 'dev'
Requires-Dist: onnxslim >=0.1.53 ; extra == 'dev'
Requires-Dist: black ~=23.1 ; extra == 'dev'
Requires-Dist: ruff ==0.1.5 ; extra == 'dev'
Provides-Extra: doc-build
Requires-Dist: accelerate ; extra == 'doc-build'
Provides-Extra: exporters
Requires-Dist: onnx ; extra == 'exporters'
Requires-Dist: timm ; extra == 'exporters'
Requires-Dist: onnxruntime ; extra == 'exporters'
Requires-Dist: protobuf >=3.20.1 ; extra == 'exporters'
Requires-Dist: transformers <4.53.0,>=4.36 ; extra == 'exporters'
Provides-Extra: exporters-gpu
Requires-Dist: onnx ; extra == 'exporters-gpu'
Requires-Dist: timm ; extra == 'exporters-gpu'
Requires-Dist: onnxruntime-gpu ; extra == 'exporters-gpu'
Requires-Dist: protobuf >=3.20.1 ; extra == 'exporters-gpu'
Requires-Dist: transformers <4.53.0,>=4.36 ; extra == 'exporters-gpu'
Provides-Extra: exporters-tf
Requires-Dist: onnx ; extra == 'exporters-tf'
Requires-Dist: timm ; extra == 'exporters-tf'
Requires-Dist: h5py ; extra == 'exporters-tf'
Requires-Dist: tf2onnx ; extra == 'exporters-tf'
Requires-Dist: onnxruntime ; extra == 'exporters-tf'
Requires-Dist: numpy <1.24.0 ; extra == 'exporters-tf'
Requires-Dist: datasets <=2.16 ; extra == 'exporters-tf'
Requires-Dist: tensorflow <=2.12.1,>=2.4 ; extra == 'exporters-tf'
Requires-Dist: transformers <4.38,>=4.36 ; extra == 'exporters-tf'
Provides-Extra: furiosa
Requires-Dist: optimum-furiosa ; extra == 'furiosa'
Provides-Extra: graphcore
Requires-Dist: optimum-graphcore ; extra == 'graphcore'
Provides-Extra: habana
Requires-Dist: optimum-habana >=1.17.0 ; extra == 'habana'
Provides-Extra: intel
Requires-Dist: optimum-intel >=1.23.0 ; extra == 'intel'
Provides-Extra: ipex
Requires-Dist: optimum-intel[ipex] >=1.23.0 ; extra == 'ipex'
Provides-Extra: neural-compressor
Requires-Dist: optimum-intel[neural-compressor] >=1.23.0 ; extra == 'neural-compressor'
Provides-Extra: neuronx
Requires-Dist: optimum-neuron[neuronx] >=0.0.28 ; extra == 'neuronx'
Provides-Extra: nncf
Requires-Dist: optimum-intel[nncf] >=1.23.0 ; extra == 'nncf'
Provides-Extra: onnxruntime
Requires-Dist: onnx ; extra == 'onnxruntime'
Requires-Dist: datasets >=1.2.1 ; extra == 'onnxruntime'
Requires-Dist: protobuf >=3.20.1 ; extra == 'onnxruntime'
Requires-Dist: onnxruntime >=1.11.0 ; extra == 'onnxruntime'
Requires-Dist: transformers <4.53.0,>=4.36 ; extra == 'onnxruntime'
Provides-Extra: onnxruntime-gpu
Requires-Dist: onnx ; extra == 'onnxruntime-gpu'
Requires-Dist: datasets >=1.2.1 ; extra == 'onnxruntime-gpu'
Requires-Dist: protobuf >=3.20.1 ; extra == 'onnxruntime-gpu'
Requires-Dist: onnxruntime-gpu >=1.11.0 ; extra == 'onnxruntime-gpu'
Requires-Dist: transformers <4.53.0,>=4.36 ; extra == 'onnxruntime-gpu'
Provides-Extra: onnxruntime-training
Requires-Dist: evaluate ; extra == 'onnxruntime-training'
Requires-Dist: torch-ort ; extra == 'onnxruntime-training'
Requires-Dist: accelerate ; extra == 'onnxruntime-training'
Requires-Dist: datasets >=1.2.1 ; extra == 'onnxruntime-training'
Requires-Dist: protobuf >=3.20.1 ; extra == 'onnxruntime-training'
Requires-Dist: transformers <4.53.0,>=4.36 ; extra == 'onnxruntime-training'
Requires-Dist: onnxruntime-training >=1.11.0 ; extra == 'onnxruntime-training'
Provides-Extra: openvino
Requires-Dist: optimum-intel[openvino] >=1.23.0 ; extra == 'openvino'
Provides-Extra: quality
Requires-Dist: black ~=23.1 ; extra == 'quality'
Requires-Dist: ruff ==0.1.5 ; extra == 'quality'
Provides-Extra: quanto
Requires-Dist: optimum-quanto >=0.2.4 ; extra == 'quanto'
Provides-Extra: tests
Requires-Dist: accelerate ; extra == 'tests'
Requires-Dist: pytest <=8.0.0 ; extra == 'tests'
Requires-Dist: requests ; extra == 'tests'
Requires-Dist: parameterized ; extra == 'tests'
Requires-Dist: pytest-xdist ; extra == 'tests'
Requires-Dist: Pillow ; extra == 'tests'
Requires-Dist: sacremoses ; extra == 'tests'
Requires-Dist: torchvision ; extra == 'tests'
Requires-Dist: torchaudio ; extra == 'tests'
Requires-Dist: einops ; extra == 'tests'
Requires-Dist: timm ; extra == 'tests'
Requires-Dist: scikit-learn ; extra == 'tests'
Requires-Dist: sentencepiece ; extra == 'tests'
Requires-Dist: rjieba ; extra == 'tests'
Requires-Dist: hf-xet ; extra == 'tests'
Requires-Dist: onnxslim >=0.1.53 ; extra == 'tests'
